{"duration": 0.1024007797241211, "input_args": {"passage": "\"L'Ethique sexuelle de l'Islam by Georges-Henri Bousquet | Bousquet was a 20th-century French jurist, economist and Islamologist. He ... He is also known for his translation work of the great Muslim authors, Al ... $10.30, \\u200e30, day returns\"", "claim": "'From source, we learn that Georges-Henri Bousquet is known for his translation work of the great Muslim authors, one of whom is listed as a Tunisian historian Ibn Khaldun (1332\u20131406).'"}, "time": 1695314010.0022626}