{"duration": 0.09637975692749023, "input_args": {"passage": "'George Albert Smith - Wikipedia | George Albert Smith Sr. (April 4, 1870 \u2013 April 4, 1951) was an American religious leader who served as the eighth president of the Church of Jesus Christ of Latter-day Saints (LDS Church)., American religious leader who served as the eighth president of the Church of Jesus Christ of Latter-day Saints (LDS Church)'", "claim": "'Source confirms that George Albert Smith was the eighth president of the Church and that he was born on April 4, 1870, in Salt Lake City.'"}, "time": 1695313818.0376906}