{"duration": 0.08368468284606934, "input_args": {"passage": "'Carl Wieland - Wikipedia | Carl Wieland (born 1950) is an Australian young earth creationist, author and speaker. He was the managing director of Creation Ministries International (formerly Answers in Genesis - Australia), a Creationist apologetics ministry., Australian young earth creationist, author and speaker\\nCarl Wieland - Wikipedia | Dr. Carl Wieland (born 1950) is an Australian young earth creationist, author and speaker. He was the managing director of Creation Ministries International (formerly Answers in Genesis - Australia), a Creationist apologetics ministry. CMI are the distributors of Creation magazine and the Journal of Creation., Creation Ministries International'", "claim": "'CMI is a creationist apologetics ministry.'"}, "time": 1695313275.1263719}