{"duration": 2.745741367340088, "input_args": {"**": "{}", "*": "['3a2eca67ae9c64320babfd5eb1d87ccc331c55e6bc647ad0786d5dc28b2f3c7d', 'Analyze the response \"You can place an order online and pick it up in-store. Here is the link with detailed instructions: https://shop.lululemon.com/story/buy-online-pick-up-in-store You can also find more information about services and hours at this link: https://shop.lululemon.com/story/services. If you have any other questions, you can contact us at 1.877.263.9300 or via Live Chat, Apple Messages, phone or email at this link: https://shop.lululemon.com/contact.\"', 2]"}, "time": 1695052150.9641697}