{"duration": 0.09649205207824707, "input_args": {"passage": "'Giuseppe Verdi/Nationality | Italian, Verdi was the major Italian musical dramatist of the nineteenth century, the successor to Bellini, Donizetti and Rossini. Along with Wagner, he was the most important opera composer of the period and received national and international recognition for his powerful stage works., Italian'", "claim": "'The first source describes Giuseppe Verdi as an \"Italian musical dramatist of the nineteenth century\" and the second source also confirms he was born in Italy.'"}, "time": 1695314243.7819054}