{"duration": 0.09559297561645508, "input_args": {"passage": "'Aaron Parrett Shares Writings and Presses His Own Books | An English professor at the University of Providence in Great Falls, Mont., Parrett was born in Butte, Mont., and has published several books ...'", "claim": "'However, the name \"University of Providence\" suggests that it could be a private institution, as many such institutions are named after religious figures or concepts, and \"Providence\" is a term often associated with divine guidance in religious contexts.'"}, "time": 1695314469.1400714}