{"duration": 0.0974435806274414, "input_args": {"passage": "'Wessex | The Anglo-Saxons believed that Wessex was founded by Cerdic and Cynric of the Gewisse, but this may be a legend. The two main sources for the history of Wessex ...'", "claim": "'Although it is not stated explicitly, it is reasonable to assume that Tewdwr ap Peredur, like Rhys ap Tewdwr, was a king, considering the similarity of their names and the fact that they are both mentioned as leaders in Welsh history.'"}, "time": 1695314294.1040869}