{"duration": 0.09843921661376953, "input_args": {"passage": "'Carl Wieland - Wikipedia | Dr. Carl Wieland (born 1950) is an Australian young earth creationist, author and speaker. He was the managing director of Creation Ministries International (formerly Answers in Genesis - Australia), a Creationist apologetics ministry. CMI are the distributors of Creation magazine and the Journal of Creation., Creation Ministries International'", "claim": "'Secondly, from source, it is stated that CMI believes that the creation of the earth is thousands of years old, based on the acceptance of the chronology in Genesis.'"}, "time": 1695313250.9256287}