{"duration": 2.0014185905456543, "input_args": {"**": "{}", "*": "['3a2eca67ae9c64320babfd5eb1d87ccc331c55e6bc647ad0786d5dc28b2f3c7d', 'Is the query \"Can I use my gift card to purchase some thing that is already discounted\" accurately addressed by the response \"Unfortunately, Gift Cards cannot be used in combination with the Sweat Collective or Military and First Responder discount for online transactions, but can be used in store. For more information, please refer to the following link: https://shop.lululemon.com/shop/luluGiftCards.jsp.\" ? Kindly answer with either \"Yes\" or \"No\".', 5]"}, "time": 1695048766.8397205}