{"duration": 0.09337925910949707, "input_args": {"passage": "'Answers in Genesis - Wikipedia | The organization sees evolution as incompatible with the Bible and believes anything other than the young Earth view is a compromise on the principle of biblical inerrancy., a compromise on the principle of biblical inerrancy'", "claim": "'Therefore, it can be inferred that CMI also views anything other than the young earth view as a compromise on the principle of biblical inerrancy.'"}, "time": 1695313233.4250085}