{"duration": 0.09826064109802246, "input_args": {"passage": "'Elie Wiesel | Books, Awards, & Facts | He was a professor at City College of New York (1972\u201376), and from 1976 he taught at Boston University, where he became Andrew W. Mellon ...'", "claim": "'From source, we see that Elie Wiesel is a professor in the Humanities at Boston University where he teaches \u201cLiterature of Memory.\u201d This is further confirmed by source, which states that he was a professor at City College of New York and then at Boston University.'"}, "time": 1695314051.5793152}