{"duration": 0.09399199485778809, "input_args": {"passage": "'Here at the End of All Things - Wikipedia | Here At The End Of All Things is a CD/DVD by American mathcore band The Number Twelve Looks Like You. It was taped on December 15, 2007, in South Hackensack, New Jersey. The title comes from a quote from the book The Lord of the Rings: The Return of the King., a CD/DVD by American mathcore band The Number Twelve Looks Like You\\nRevisiting Parallel Context Windows: A Frustratingly ... | Who wrote the book that inspired the name of the CD/DVD \"Here at the End of All Things\"? ... The title comes from a quote from the book The Lord of the Rings: The ...'", "claim": "'The CD/DVD \"Here at the End of All Things\" by American mathcore band The Number Twelve Looks Like You is named after a quote from the book The Lord of the Rings: The Return of the King.'"}, "time": 1695313620.1599064}